{
  "block": {
    "miniDapp": "block1.0.16.minidapp",
    "icon": "block/assets/blockLogoThumbnail.svg",
    "conf": "block/minidapp.conf"
  },
  "futurecash1": {
    "miniDapp": "futurecash11.0.1.minidapp",
    "icon": "futurecash/futurecash.svg",
    "conf": "futurecash/minidapp.conf"
  },
  "scriptide": {
    "miniDapp": "scriptide0.5.0.minidapp",
    "icon": "scriptide/images/icon.png",
    "conf": "scriptide/minidapp.conf"
  },
  "storefront": {
    "miniDapp": "storefront1.0.5.minidapp",
    "icon": "images/storeIcon.png",
    "conf": "minidapp.conf"
  },
  "terminal": {
    "miniDapp": "terminal1.1.0.minidapp",
    "icon": "terminal/terminal_icon.png",
    "conf": "terminal/minidapp.conf"
  },
  "wallet": {
    "miniDapp": "wallet1.1.5.minidapp",
    "icon": "minidapp/wallet/assets/minima-logo-box.svg",
    "conf": "minidapp/wallet/minidapp.conf"
  }
}
